evedata/__init__.py
evedata/__pycache__/__init__.cpython-39.pyc
evedata/evefile/__init__.py
evedata/evefile/__pycache__/__init__.cpython-39.pyc
evedata/evefile/boundaries/__init__.py
evedata/evefile/boundaries/evefile.py
evedata/evefile/boundaries/eveh5.py
evedata/evefile/boundaries/__pycache__/__init__.cpython-39.pyc
evedata/evefile/boundaries/__pycache__/evefile.cpython-39.pyc
evedata/evefile/boundaries/__pycache__/eveh5.cpython-39.pyc
evedata/evefile/controllers/__init__.py
evedata/evefile/controllers/info.py
evedata/evefile/controllers/mpskip.py
evedata/evefile/controllers/preprocessing.py
evedata/evefile/controllers/version_mapping.py
evedata/evefile/controllers/__pycache__/__init__.cpython-39.pyc
evedata/evefile/controllers/__pycache__/info.cpython-39.pyc
evedata/evefile/controllers/__pycache__/mpskip.cpython-39.pyc
evedata/evefile/controllers/__pycache__/preprocessing.cpython-39.pyc
evedata/evefile/controllers/__pycache__/version_mapping.cpython-39.pyc
evedata/evefile/entities/__init__.py
evedata/evefile/entities/data.py
evedata/evefile/entities/file.py
evedata/evefile/entities/metadata.py
evedata/evefile/entities/__pycache__/__init__.cpython-39.pyc
evedata/evefile/entities/__pycache__/data.cpython-39.pyc
evedata/evefile/entities/__pycache__/file.cpython-39.pyc
evedata/evefile/entities/__pycache__/metadata.cpython-39.pyc
evedata/measurement/__init__.py
evedata/measurement/__pycache__/__init__.cpython-39.pyc
evedata/measurement/boundaries/__init__.py
evedata/measurement/boundaries/measurement.py
evedata/measurement/boundaries/__pycache__/__init__.cpython-39.pyc
evedata/measurement/boundaries/__pycache__/measurement.cpython-39.pyc
evedata/measurement/controllers/__init__.py
evedata/measurement/controllers/joining.py
evedata/measurement/controllers/__pycache__/__init__.cpython-39.pyc
evedata/measurement/controllers/__pycache__/filling.cpython-39.pyc
evedata/measurement/controllers/__pycache__/joining.cpython-39.pyc
evedata/measurement/entities/__init__.py
evedata-0.1.0rc1.dist-info/licenses/COPYING
evedata-0.1.0rc1.dist-info/licenses/LICENSE
evedata-0.1.0rc1.dist-info/METADATA
evedata-0.1.0rc1.dist-info/WHEEL
evedata-0.1.0rc1.dist-info/top_level.txt
evedata-0.1.0rc1.dist-info/RECORD
